eagle2svg/__init__.py
eagle2svg/eagle_element.py
eagle2svg/eagle_parser.py
eagle2svg/eagle_types.py
eagle2svg/render.py
eagle2svg/svg_common.py
eagle2svg-0.1.5.dist-info/METADATA
eagle2svg-0.1.5.dist-info/WHEEL
eagle2svg-0.1.5.dist-info/entry_points.txt
eagle2svg-0.1.5.dist-info/top_level.txt
eagle2svg-0.1.5.dist-info/RECORD
