Metadata-Version: 2.1
Name: eagle2svg
Version: 0.1.5
Summary: Eagle CAD file to svg renderer
Author-email: Atsushi Watanabe <atsushi.w@ieee.org>
License: BSD
Project-URL: Homepage, https://github.com/at-wat/eagle2svg
Requires-Python: >=3.8
Requires-Dist: xmltodict
